{
    "chnroutes2": {
        "cargoLocks": null,
        "date": "2024-04-25",
        "extract": null,
        "name": "chnroutes2",
        "passthru": null,
        "pinned": false,
        "src": {
            "deepClone": false,
            "fetchSubmodules": false,
            "leaveDotGit": false,
            "name": null,
            "owner": "misakaio",
            "repo": "chnroutes2",
            "rev": "59752fd7f9438a8305ece944e71ba45b9b57775e",
            "sha256": "sha256-yZN7b7dhYu2qX9WHNWUY8xpSuilYdDJ4sp16aCV+XDY=",
            "type": "github"
        },
        "version": "59752fd7f9438a8305ece944e71ba45b9b57775e"
    },
    "dnsmasq-china-list": {
        "cargoLocks": null,
        "date": "2024-04-25",
        "extract": null,
        "name": "dnsmasq-china-list",
        "passthru": null,
        "pinned": false,
        "src": {
            "deepClone": false,
            "fetchSubmodules": false,
            "leaveDotGit": false,
            "name": null,
            "owner": "felixonmars",
            "repo": "dnsmasq-china-list",
            "rev": "3713f09710000af0a78d0b467f6817365976058c",
            "sha256": "sha256-BrvNgnUIHPqHe4HK0SLy/1Ya9tqAc2RcfU9sGUjScbg=",
            "type": "github"
        },
        "version": "3713f09710000af0a78d0b467f6817365976058c"
    },
    "metacubexd": {
        "cargoLocks": null,
        "date": null,
        "extract": null,
        "name": "metacubexd",
        "passthru": null,
        "pinned": false,
        "src": {
            "name": null,
            "sha256": "sha256-l2mcb2optvgtfzma/Ix63Y8BxXC6CsGoyIIMoOvD074=",
            "type": "url",
            "url": "https://github.com/MetaCubeX/metacubexd/releases/download/v1.138.1/compressed-dist.tgz"
        },
        "version": "v1.138.1"
    },
    "telegram-desktop-megumifox": {
        "cargoLocks": null,
        "date": "2024-04-25",
        "extract": null,
        "name": "telegram-desktop-megumifox",
        "passthru": null,
        "pinned": false,
        "src": {
            "name": null,
            "sha256": "sha256-IQiyJPbFZ0XSSZbcMYS0J1dej5G5LRx4qB/frW7QtnA=",
            "type": "url",
            "url": "https://raw.githubusercontent.com/archlinuxcn/repo/e5a6a3e1e0d837f86d7ffdd69dbcc00c217950ac/archlinuxcn/telegram-desktop-megumifox/0001-Use-font-from-environment-variables.patch"
        },
        "version": "e5a6a3e1e0d837f86d7ffdd69dbcc00c217950ac"
    }
}